promql_parser/__init__.py
promql_parser/__init__.pyi
promql_parser/promql_parser.cpython-312-powerpc64le-linux-gnu.so
promql_parser/py.typed
promql_parser-0.7.0.dist-info/METADATA
promql_parser-0.7.0.dist-info/WHEEL
promql_parser-0.7.0.dist-info/licenses/LICENSE
promql_parser-0.7.0.dist-info/RECORD
