Metadata-Version: 2.4
Name: promql-parser
Version: 0.7.0
Classifier: Programming Language :: Rust
Classifier: Programming Language :: Python :: Implementation :: CPython
Classifier: Programming Language :: Python :: Implementation :: PyPy
License-File: LICENSE
Requires-Python: >=3.8
Project-URL: Source Code, https://github.com/messense/py-promql-parser
